xonv/__init__.py
xonv/layer/__init__.py
xonv/layer/extended_conv_layer.py
xonv/loss_landscape/__init__.py
xonv/loss_landscape/eval_loss_landscape.py
xonv/loss_landscape/loss_landscape_utils.py
xonv/loss_landscape/plot_landscape.py
xonv/model/__init__.py
xonv/model/regression_model.py
xonv/utils/__init__.py
xonv/utils/config.py
xonv/utils/custom_lr_decay.py
xonv/utils/hyperparam_utils.py
xonv/utils/project_path.py
xonv/utils/upload_to_dropbox.py
xonv-0.2.5.dist-info/LICENSE
xonv-0.2.5.dist-info/METADATA
xonv-0.2.5.dist-info/WHEEL
xonv-0.2.5.dist-info/top_level.txt
xonv-0.2.5.dist-info/RECORD
