Metadata-Version: 2.1
Name: xonv
Version: 0.2.5
Summary: xonv: Extended convolutional layers
Home-page: https://github.com/alisiahkoohi/xonv
Author: Ali Siahkoohi
Author-email: alisk@rice.edu
Classifier: Programming Language :: Python :: 3
Classifier: License :: OSI Approved :: MIT License
Classifier: Operating System :: OS Independent
Requires-Python: >=3.10
License-File: LICENSE
Requires-Dist: matplotlib
Requires-Dist: seaborn
Requires-Dist: numpy
Requires-Dist: tqdm
Requires-Dist: h5py
Requires-Dist: gitpython
Requires-Dist: torch
Requires-Dist: colorcet
Provides-Extra: pytorch
Requires-Dist: torch; extra == "pytorch"
Requires-Dist: torch-cuda; extra == "pytorch"
